[{"id":"7751f1ce.2d5b3","type":"tab","label":"Flow 1","disabled":false,"info":""},{"id":"7493e9ee.4b09e8","type":"comment","z":"7751f1ce.2d5b3","name":"Node-Red y Git","info":"","x":360,"y":100,"wires":[]},{"id":"d3d17b24.dcad38","type":"inject","z":"7751f1ce.2d5b3","name":"","topic":"","payload":"","payloadType":"date","repeat":"","crontab":"","once":false,"onceDelay":0.1,"x":260,"y":200,"wires":[[]]},{"id":"dfedcf22.262e2","type":"debug","z":"7751f1ce.2d5b3","name":"","active":true,"tosidebar":true,"console":false,"tostatus":false,"complete":"false","x":660,"y":200,"wires":[]}]